<annotation>
	<folder>JPEGImages</folder>
	<filename>076.jpg</filename>
	<path>\content\YOLOX\datasets\VOCdevkit\VOC2007\JPEGImages\076.jpg</path>
	<source>
		<database>Unknown</database>
	</source>
	<size>
		<width>604</width>
		<height>456</height>
		<depth>3</depth>
	</size>
	<segmented>0</segmented>
	<object>
		<name>graffity</name>
		<pose>Unspecified</pose>
		<truncated>0</truncated>
		<difficult>0</difficult>
		<bndbox>
			<xmin>5</xmin>
			<ymin>117</ymin>
			<xmax>599</xmax>
			<ymax>291</ymax>
		</bndbox>
	</object>
	<object>
		<name>graffity</name>
		<pose>Unspecified</pose>
		<truncated>1</truncated>
		<difficult>0</difficult>
		<bndbox>
			<xmin>1</xmin>
			<ymin>231</ymin>
			<xmax>602</xmax>
			<ymax>391</ymax>
		</bndbox>
	</object>
	<object>
		<name>graffity</name>
		<pose>Unspecified</pose>
		<truncated>0</truncated>
		<difficult>0</difficult>
		<bndbox>
			<xmin>415</xmin>
			<ymin>105</ymin>
			<xmax>576</xmax>
			<ymax>134</ymax>
		</bndbox>
	</object>
	<object>
		<name>graffity</name>
		<pose>Unspecified</pose>
		<truncated>0</truncated>
		<difficult>0</difficult>
		<bndbox>
			<xmin>7</xmin>
			<ymin>152</ymin>
			<xmax>218</xmax>
			<ymax>178</ymax>
		</bndbox>
	</object>
</annotation>
