<annotation>
	<folder>JPEGImages</folder>
	<filename>063.jpg</filename>
	<path>\content\YOLOX\datasets\VOCdevkit\VOC2012\JPEGImages\063.jpg</path>
	<source>
		<database>Unknown</database>
	</source>
	<size>
		<width>2560</width>
		<height>1920</height>
		<depth>3</depth>
	</size>
	<segmented>0</segmented>
	<object>
		<name>graffity</name>
		<pose>Unspecified</pose>
		<truncated>0</truncated>
		<difficult>0</difficult>
		<bndbox>
			<xmin>16</xmin>
			<ymin>341</ymin>
			<xmax>2283</xmax>
			<ymax>1892</ymax>
		</bndbox>
	</object>
	<object>
		<name>graffity</name>
		<pose>Unspecified</pose>
		<truncated>0</truncated>
		<difficult>0</difficult>
		<bndbox>
			<xmin>2111</xmin>
			<ymin>723</ymin>
			<xmax>2552</xmax>
			<ymax>1227</ymax>
		</bndbox>
	</object>
	<object>
		<name>graffity</name>
		<pose>Unspecified</pose>
		<truncated>0</truncated>
		<difficult>0</difficult>
		<bndbox>
			<xmin>1824</xmin>
			<ymin>1406</ymin>
			<xmax>2379</xmax>
			<ymax>1898</ymax>
		</bndbox>
	</object>
</annotation>
